funfrp/__init__.py
funfrp-0.1.3.dist-info/METADATA
funfrp-0.1.3.dist-info/WHEEL
funfrp-0.1.3.dist-info/top_level.txt
funfrp-0.1.3.dist-info/RECORD
