Metadata-Version: 2.4
Name: funfrp
Version: 0.1.3
Summary: funfrp
Author-email: niuliangtao <farfarfun@qq.com>
Requires-Python: >=3.8
